pysnapping/__init__.py
pysnapping/linear_referencing.py
pysnapping/py.typed
pysnapping/snap.py
pysnapping/stats.py
pysnapping/util.py
pysnapping/test/__init__.py
pysnapping/test/complex_trip.geojson
pysnapping/test/conftest.py
pysnapping/test/test_linear_referencing.py
pysnapping/test/test_snap.py
pysnapping/test/test_util.py
pysnapping-0.2.2.dist-info/LICENSE
pysnapping-0.2.2.dist-info/METADATA
pysnapping-0.2.2.dist-info/WHEEL
pysnapping-0.2.2.dist-info/top_level.txt
pysnapping-0.2.2.dist-info/RECORD
