Metadata-Version: 2.2
Name: pysnapping
Version: 0.2.2
Summary: Snap points to a line string keeping a given order or spacing intact
Author-email: Alexander Held | geOps <alexander.held@geops.com>
Maintainer-email: Alexander Held | geOps <alexander.held@geops.com>
License: MIT License
Project-URL: homepage, https://github.com/geops/pysnapping
Project-URL: geOps, https://geops.com/en
Keywords: snapping,projecting,linear referencing,order,linestring,GIS,GTFS,kilometrage,DAG,shortest path
Classifier: Development Status :: 4 - Beta
Classifier: Programming Language :: Python :: 3
Classifier: Intended Audience :: Developers
Classifier: License :: OSI Approved :: MIT License
Classifier: Topic :: Scientific/Engineering :: GIS
Classifier: Topic :: Software Development :: Libraries :: Python Modules
Classifier: Typing :: Typed
Requires-Python: >=3.9
License-File: LICENSE
Requires-Dist: shapely
Requires-Dist: numpy<2
Requires-Dist: pyproj>=3.2.0
